wwai_sdk/__init__.py
wwai_sdk/cache.py
wwai_sdk/decrypt_util.py
wwai_sdk/utils.py
wwai_sdk/wwai_client.py
wwai_sdk/__pycache__/__init__.cpython-311.pyc
wwai_sdk-0.0.20.dist-info/METADATA
wwai_sdk-0.0.20.dist-info/WHEEL
wwai_sdk-0.0.20.dist-info/top_level.txt
wwai_sdk-0.0.20.dist-info/RECORD
