Metadata-Version: 2.1
Name: wwai_sdk
Version: 0.0.20
Summary: 万网AI云平台SDK
Home-page: 
Author: mrhua
Author-email: 
Classifier: Programming Language :: Python :: 3
Classifier: License :: OSI Approved :: MIT License
Classifier: Operating System :: OS Independent
Requires-Python: >=3.8
Requires-Dist: requests
Requires-Dist: diskcache
Requires-Dist: redis
Requires-Dist: cryptography
Requires-Dist: pycryptodome
Requires-Dist: requests-toolbelt
